loggerly/__init__.py
loggerly/loggerly.py
loggerly-0.0.2.dist-info/LICENSE
loggerly-0.0.2.dist-info/METADATA
loggerly-0.0.2.dist-info/WHEEL
loggerly-0.0.2.dist-info/top_level.txt
loggerly-0.0.2.dist-info/RECORD
